README.md
setup.py
argeasy/__init__.py
argeasy/argeasy.py
argeasy/arguments.py
argeasy/exceptions.py
argeasy.egg-info/PKG-INFO
argeasy.egg-info/SOURCES.txt
argeasy.egg-info/dependency_links.txt
argeasy.egg-info/top_level.txt