Metadata-Version: 2.1
Name: argeasy
Version: 3.1.0
Summary: ArgEasy: Create amazing CLI programs.
Home-page: https://github.com/jaedsonpys/argeasy
Author: Jaedson Silva
Author-email: jaedson.dev@proton.me
License: MIT
Project-URL: License, https://github.com/jaedsonpys/argeasy/blob/master/LICENSE
Keywords: cli,command,argument,parser,command-line,interface
Platform: UNKNOWN
Classifier: Development Status :: 5 - Production/Stable
Classifier: Intended Audience :: Developers
Classifier: License :: OSI Approved :: MIT License
Classifier: Operating System :: OS Independent
Classifier: Programming Language :: Python :: 3
